ShujujiegouYuSuanfaFenxiXuexiBijiLuocong/README.md
ShujujiegouYuSuanfaFenxiXuexiBijiLuocong/__init__.py
ShujujiegouYuSuanfaFenxiXuexiBijiLuocong/__main__.py
ShujujiegouYuSuanfaFenxiXuexiBijiLuocong/file.epub
ShujujiegouYuSuanfaFenxiXuexiBijiLuocong/index.html
ShujujiegouYuSuanfaFenxiXuexiBijiLuocong/css/__init__.py
ShujujiegouYuSuanfaFenxiXuexiBijiLuocong/css/annotations.css
ShujujiegouYuSuanfaFenxiXuexiBijiLuocong/css/main.css
ShujujiegouYuSuanfaFenxiXuexiBijiLuocong/css/normalize.css
ShujujiegouYuSuanfaFenxiXuexiBijiLuocong/css/popup.css
ShujujiegouYuSuanfaFenxiXuexiBijiLuocong/font/__init__.py
ShujujiegouYuSuanfaFenxiXuexiBijiLuocong/font/fontello.eot
ShujujiegouYuSuanfaFenxiXuexiBijiLuocong/font/fontello.svg
ShujujiegouYuSuanfaFenxiXuexiBijiLuocong/font/fontello.ttf
ShujujiegouYuSuanfaFenxiXuexiBijiLuocong/font/fontello.woff
ShujujiegouYuSuanfaFenxiXuexiBijiLuocong/img/__init__.py
ShujujiegouYuSuanfaFenxiXuexiBijiLuocong/img/annotator-glyph-sprite.png
ShujujiegouYuSuanfaFenxiXuexiBijiLuocong/img/annotator-icon-sprite.png
ShujujiegouYuSuanfaFenxiXuexiBijiLuocong/img/apple-touch-icon.png
ShujujiegouYuSuanfaFenxiXuexiBijiLuocong/img/cancelfullscreen.png
ShujujiegouYuSuanfaFenxiXuexiBijiLuocong/img/close.png
ShujujiegouYuSuanfaFenxiXuexiBijiLuocong/img/fullscreen.png
ShujujiegouYuSuanfaFenxiXuexiBijiLuocong/img/loader.gif
ShujujiegouYuSuanfaFenxiXuexiBijiLuocong/img/menu-icon.png
ShujujiegouYuSuanfaFenxiXuexiBijiLuocong/img/save.png
ShujujiegouYuSuanfaFenxiXuexiBijiLuocong/img/saved.png
ShujujiegouYuSuanfaFenxiXuexiBijiLuocong/img/settings-s.png
ShujujiegouYuSuanfaFenxiXuexiBijiLuocong/img/settings.png
ShujujiegouYuSuanfaFenxiXuexiBijiLuocong/img/star.png
ShujujiegouYuSuanfaFenxiXuexiBijiLuocong/js/__init__.py
ShujujiegouYuSuanfaFenxiXuexiBijiLuocong/js/epub.js
ShujujiegouYuSuanfaFenxiXuexiBijiLuocong/js/epub.min.js
ShujujiegouYuSuanfaFenxiXuexiBijiLuocong/js/epub.min.map
ShujujiegouYuSuanfaFenxiXuexiBijiLuocong/js/hooks.min.js
shujujiegou_yu_suanfa_fenxi_xuexi_biji_luocong-2024.3.2.0.dist-info/METADATA
shujujiegou_yu_suanfa_fenxi_xuexi_biji_luocong-2024.3.2.0.dist-info/WHEEL
shujujiegou_yu_suanfa_fenxi_xuexi_biji_luocong-2024.3.2.0.dist-info/entry_points.txt
shujujiegou_yu_suanfa_fenxi_xuexi_biji_luocong-2024.3.2.0.dist-info/top_level.txt
shujujiegou_yu_suanfa_fenxi_xuexi_biji_luocong-2024.3.2.0.dist-info/RECORD
